{"count": "27", "directions": [{"text": "Fry the onions gently in the oil until they are translucent, approximately 20 minutes.", "ord": "1"}, {"text": "Add the Garlic and Ginger.  Fry gently for 5 minutes more.", "ord": "2"}, {"text": "Add the whole spices and fry for 15 more minutes.  The onions shoulc appear lightly golden.", "ord": "3"}, {"text": "Add the powdered spices and fry them for two minutes.", "ord": "4"}, {"text": "Turn up the stove to high, and add the Tomatoes.  Cook until the tomatoes are hot.", "ord": "5"}, {"text": "Add the Chicken,  get it it hot also, then fry it for 6 minutes.", "ord": "6"}, {"text": "Heat the water to boiling, separately, then add it to the Curry.", "ord": "7"}, {"text": "Bring to a boil, reduce the heat, and simmer very gently for an additional 20 minutes, or until the chicken is cooked.", "ord": "8"}], "title": "Copy of Jiten's standard meat curry with onion and tomato", "row_count": "20", "ingredients": [{"comment": "NIL", "amount": "2", "measure": "Pieces", "ord": "1", "ingredient": "onion, cut in lengthwise slivers"}, {"comment": "NIL", "amount": "1/4", "measure": "Cup", "ord": "2", "ingredient": "Oil"}, {"comment": "NIL", "amount": "1", "measure": "T.", "ord": "3", "ingredient": "garlic, finely chopped"}, {"comment": "NIL", "amount": "3-4", "measure": "T.", "ord": "4", "ingredient": "ginger, finely chopped"}, {"comment": "NIL", "amount": null, "measure": "SectionHeading", "ord": "5", "ingredient": null}, {"comment": "NIL", "amount": "2", "measure": "Pieces", "ord": "6", "ingredient": "Cinnamon"}, {"comment": "NIL", "amount": "6", "measure": "Pieces", "ord": "7", "ingredient": "White Cardamom, whole"}, {"comment": "NIL", "amount": "5", "measure": "Count", "ord": "8", "ingredient": "Black Cardamom, whole"}, {"comment": "NIL", "amount": "8", "measure": "Pieces", "ord": "9", "ingredient": "clove"}, {"comment": "NIL", "amount": "8", "measure": "Count", "ord": "10", "ingredient": "Bay Leaves"}, {"comment": "NIL", "amount": "5", "measure": "Count", "ord": "11", "ingredient": "Chillies, dry or green, whole"}, {"comment": "NIL", "amount": null, "measure": "SectionHeading", "ord": "12", "ingredient": null}, {"comment": "1", "amount": "1", "measure": "T.", "ord": "13", "ingredient": "Turmeric"}, {"comment": "can substitute nutmeg", "amount": "1/2", "measure": "t.", "ord": "14", "ingredient": "Mace"}, {"comment": "NIL", "amount": null, "measure": "SectionHeading", "ord": "14", "ingredient": null}, {"comment": "NIL", "amount": "28", "measure": "Ounce", "ord": "15", "ingredient": "tomatoes, canned"}, {"comment": "NIL", "amount": "2-1/2", "measure": "Pound", "ord": "16", "ingredient": "meat, cut for curry"}, {"comment": "NIL", "amount": "3", "measure": "Cup", "ord": "17", "ingredient": "water"}]}